{"tokens": ["6", "-", "Andre", "Agassi", "(", "U.S.", ")", "vs.", "Mauricio", "Hadad", "(", "Colombia", ")"], "entity": [{"text": "Andre Agassi", "offset": [2, 4], "type": "PER"}, {"text": "U.S.", "offset": [5, 6], "type": "LOC"}, {"text": "Mauricio Hadad", "offset": [8, 10], "type": "PER"}, {"text": "Colombia", "offset": [11, 12], "type": "LOC"}], "index": 713}
{"tokens": ["\"", "Windows", "95", "is", "going", "to", "do", "great", ",", "\"", "he", "said", ".", "\""], "entity": [{"text": "Windows 95", "offset": [1, 3], "type": "MISC"}], "index": 3076}
{"tokens": ["The", "Springboks", "would", "have", "gone", "ahead", "had", "not", "fly-half", "Joel", "Stransky", "'s", "conversion", "hit", "an", "upright", "and", "New", "Zealand", "only", "scrambled", "to", "safety", "through", "a", "fine", "penalty", "from", "replacement", "fly-half", "Jon", "Preston", "and", "a", "drop", "goal", "by", "number", "eight", "Zinzan", "Brooke", "."], "entity": [{"text": "Springboks", "offset": [1, 2], "type": "ORG"}, {"text": "Joel Stransky", "offset": [9, 11], "type": "PER"}, {"text": "New Zealand", "offset": [17, 19], "type": "LOC"}, {"text": "Jon Preston", "offset": [30, 32], "type": "PER"}, {"text": "Zinzan Brooke", "offset": [39, 41], "type": "PER"}], "index": 3731}
{"tokens": ["Chamorro", "has", "complained", "of", "lower", "back", "pain", "since", "her", "trip", "to", "Taiwan", "in", "May", ",", "when", "the", "pain", "forced", "her", "to", "go", "to", "Taipei", "University", "Hospital", "for", "an", "examination", "."], "entity": [{"text": "Chamorro", "offset": [0, 1], "type": "PER"}, {"text": "Taiwan", "offset": [11, 12], "type": "LOC"}, {"text": "Taipei University Hospital", "offset": [23, 26], "type": "LOC"}], "index": 4251}
{"tokens": ["Luke", "Jensen", "and", "Murphy", "Jensen", "(", "U.S.", ")", "beat", "Alexander", "Volkov"], "entity": [{"text": "Luke Jensen", "offset": [0, 2], "type": "PER"}, {"text": "Murphy Jensen", "offset": [3, 5], "type": "PER"}, {"text": "U.S.", "offset": [6, 7], "type": "LOC"}, {"text": "Alexander Volkov", "offset": [9, 11], "type": "PER"}], "index": 4536}
{"tokens": ["Hanwha", "55", "1", "48", ".534", "8"], "entity": [{"text": "Hanwha", "offset": [0, 1], "type": "ORG"}], "index": 5321}
{"tokens": ["MSV", "Duisberg", "0", "Bayern", "Munich", "4"], "entity": [{"text": "MSV Duisberg", "offset": [0, 2], "type": "ORG"}, {"text": "Bayern Munich", "offset": [3, 5], "type": "ORG"}], "index": 5536}
{"tokens": ["Ipswich", ",", "Port", "Vale", "v", "Oxford", ",", "Reading", "v", "Stoke", ",", "Southend", "v"], "entity": [{"text": "Ipswich", "offset": [0, 1], "type": "ORG"}, {"text": "Port Vale", "offset": [2, 4], "type": "ORG"}, {"text": "Oxford", "offset": [5, 6], "type": "ORG"}, {"text": "Reading", "offset": [7, 8], "type": "ORG"}, {"text": "Stoke", "offset": [9, 10], "type": "ORG"}, {"text": "Southend", "offset": [11, 12], "type": "ORG"}], "index": 6537}
{"tokens": ["SOCCER", "-", "AFRICAN", "NATIONS", "CUP", "COLLATED", "RESULTS", "."], "entity": [{"text": "AFRICAN NATIONS CUP", "offset": [2, 5], "type": "MISC"}], "index": 6588}
{"tokens": ["Talbott", "to", "meet", "Russian", ",", "Canadian", "counterparts", "."], "entity": [{"text": "Talbott", "offset": [0, 1], "type": "PER"}, {"text": "Russian", "offset": [3, 4], "type": "MISC"}, {"text": "Canadian", "offset": [5, 6], "type": "MISC"}], "index": 7643}
{"tokens": ["Almost", "entirely", "paralyzed", ",", "Reeve", "underwent", "extensive", "surgery", "to", "fuse", "the", "vertebrae", "to", "the", "base", "of", "the", "skull", "and", "prevent", "any", "further", "damage", "to", "his", "spine", "."], "entity": [{"text": "Reeve", "offset": [4, 5], "type": "PER"}], "index": 7710}
{"tokens": ["Drew", "said", "Peiris", ",", "a", "bird", "enthusiast", ",", "would", "have", "succeeded", "with", "the", "fraud", "if", "he", "had", "not", "tried", "to", "trade", "a", "fourth", "pair", "of", "bogus", "birds", "after", "an", "associate", "had", "told", "police", "of", "the", "scam", "."], "entity": [{"text": "Drew", "offset": [0, 1], "type": "PER"}, {"text": "Peiris", "offset": [2, 3], "type": "PER"}], "index": 9796}
{"tokens": ["8.", "Jose", "Moreno", "(", "Spain", ")", "1:05.219"], "entity": [{"text": "Jose Moreno", "offset": [1, 3], "type": "PER"}, {"text": "Spain", "offset": [4, 5], "type": "LOC"}], "index": 10110}
{"tokens": ["TEXAS", "AT", "KANSAS", "CITY"], "entity": [{"text": "TEXAS", "offset": [0, 1], "type": "ORG"}, {"text": "KANSAS CITY", "offset": [2, 4], "type": "LOC"}], "index": 10453}
{"tokens": ["UEFA", "Cup", "hopefuls", "Parma", "and", "Roma", ",", "under", "new", "coaches", "this", "season", ",", "crashed", "out", "of", "the", "Italian", "Cup", "to", "second", "division", "opponents", "on", "Wednesday", "while", "league", "champions", "Milan", "could", "only", "draw", "1-1", "at", "humble", "Empoli", "."], "entity": [{"text": "UEFA Cup", "offset": [0, 2], "type": "MISC"}, {"text": "Parma", "offset": [3, 4], "type": "ORG"}, {"text": "Roma", "offset": [5, 6], "type": "ORG"}, {"text": "Italian Cup", "offset": [17, 19], "type": "MISC"}, {"text": "Milan", "offset": [28, 29], "type": "ORG"}, {"text": "Empoli", "offset": [35, 36], "type": "ORG"}], "index": 10571}
{"tokens": ["ISS", "said", "that", "the", "deal", "included", "ISS", "Inc", "operations", "in", "Mexico", "and", "the", "sale", "of", "ISS", "Inc", "interests", "in", "Brazil", "would", "be", "discussed", "."], "entity": [{"text": "ISS", "offset": [0, 1], "type": "ORG"}, {"text": "ISS Inc", "offset": [6, 8], "type": "ORG"}, {"text": "Mexico", "offset": [10, 11], "type": "LOC"}, {"text": "ISS Inc", "offset": [15, 17], "type": "ORG"}, {"text": "Brazil", "offset": [19, 20], "type": "LOC"}], "index": 12146}
{"tokens": ["Pakistan", ":", "Aamir", "Sohail", ",", "Saeed", "Anwar", ",", "Ijaz", "Ahmed", ",", "Inzamam-ul-Haq", ",", "Salim", "Malik", ",", "Wasim", "Akram", "(", "captain", ")", ",", "Moin", "Khan", ",", "Mushtaq", "Ahmed", ",", "Waqar", "Younis", ",", "Ata-ur-Rehman", ",", "Saqlain", "Mushtaq", "."], "entity": [{"text": "Pakistan", "offset": [0, 1], "type": "LOC"}, {"text": "Aamir Sohail", "offset": [2, 4], "type": "PER"}, {"text": "Saeed Anwar", "offset": [5, 7], "type": "PER"}, {"text": "Ijaz Ahmed", "offset": [8, 10], "type": "PER"}, {"text": "Inzamam-ul-Haq", "offset": [11, 12], "type": "PER"}, {"text": "Salim Malik", "offset": [13, 15], "type": "PER"}, {"text": "Wasim Akram", "offset": [16, 18], "type": "PER"}, {"text": "Moin Khan", "offset": [22, 24], "type": "PER"}, {"text": "Mushtaq Ahmed", "offset": [25, 27], "type": "PER"}, {"text": "Waqar Younis", "offset": [28, 30], "type": "PER"}, {"text": "Ata-ur-Rehman", "offset": [31, 32], "type": "PER"}, {"text": "Saqlain Mushtaq", "offset": [33, 35], "type": "PER"}], "index": 12371}
{"tokens": ["3", "-", "Arantxa", "Sanchez", "Vicario", "(", "Spain", ")", "beat", "Nicole", "Arendt", "(", "U.S.", ")"], "entity": [{"text": "Arantxa Sanchez Vicario", "offset": [2, 5], "type": "PER"}, {"text": "Spain", "offset": [6, 7], "type": "LOC"}, {"text": "Nicole Arendt", "offset": [9, 11], "type": "PER"}, {"text": "U.S.", "offset": [12, 13], "type": "LOC"}], "index": 12502}
{"tokens": ["Workers", "at", "Serbia", "'s", "Zastava", "arms", "factory", "entered", "the", "ninth", "day", "of", "their", "protest", "over", "unpaid", "wages", "on", "Thursday", "with", "management", "accused", "them", "of", "rejecting", "talks", "."], "entity": [{"text": "Serbia", "offset": [2, 3], "type": "LOC"}, {"text": "Zastava", "offset": [4, 5], "type": "ORG"}], "index": 12874}
{"tokens": ["Thieves", "stole", "almost", "2,000", "Irish", "pounds", "(", "$", "3,000", ")", "from", "the", "officers", "'", "canteen", "of", "a", "Limerick", "jail", "on", "Thursday", "while", "warders", "slept", "in", "a", "room", "upstairs", "."], "entity": [{"text": "Irish", "offset": [4, 5], "type": "MISC"}, {"text": "Limerick", "offset": [17, 18], "type": "LOC"}], "index": 13592}
