{"tokens": ["RT", "@BestVinesEver", ":", "When", "coach", "called", "Johnny", "to", "tell", "him", "he", "'s", "starting", "Sunday", "[URL]"], "entity": [{"text": "Johnny", "offset": [6, 7], "type": "person"}]}
{"tokens": ["RT", "@TomSilverstein", ":", "New", "from", "JS", ":", "Frustration", "'", "extremely", "high", "'", "for", "Slocum", "after", "7th", "blocked", "kick", "[URL]", "#packers"], "entity": [{"text": "Slocum", "offset": [13, 14], "type": "person"}]}
{"tokens": ["@usnOOzin", "Ahh", "Steve", ",", "you're", "so", "good", "to", "me", ",", "every", "week", ".", "#FF", ".", "Thanks", "so", "much", ".", "How", "'s", "the", "wife", "recovering", "???"], "entity": [{"text": "Steve", "offset": [2, 3], "type": "person"}]}
{"tokens": ["Amber", "Le", "Bon", "is", "to", "walk", "in", "Giles", "Deacon", "'s", "Monday", "LFW", "show"], "entity": [{"text": "Amber Le Bon", "offset": [0, 3], "type": "person"}, {"text": "Giles Deacon", "offset": [7, 9], "type": "person"}]}
{"tokens": ["3rd", "qtr", "has", "begun", "......", "Harris", "starts", "us", "off", "with", "a", "3", "!!!"], "entity": [{"text": "Harris", "offset": [5, 6], "type": "person"}]}
{"tokens": ["@Strigy", "got", "mine", "in", "bbt", "aintree", "today", ".", "Played", "table", "tennis", "on", "it", "in", "store", "!", "V", "impressed", ".", "Did", "you", "get", "analogue", "controller", "2", "?"], "entity": [{"text": "aintree", "offset": [5, 6], "type": "location"}]}
{"tokens": ["RT", "@JaredLeto", ":", "Hope", "all", "our", "friends", "in", "Russia", "take", "the", "grand", "tour", "in", "March", "!!", "Xo", "[URL]", "#LoveLustTour"], "entity": [{"text": "Russia", "offset": [8, 9], "type": "location"}]}
{"tokens": ["\"", "@JAYnFRESH", ":", "@BTAUKammyCakes_", "come", "see", "us", "on", "the", "31st", "\"", "I", "Cant", "I", "Gotta", "Step", "Performance", "at", "Tha", "OaklandArtsSchool", "Thing", "If", "I", "Couldve", "I", "Wouldve"], "entity": [{"text": "OaklandArtsSchool", "offset": [19, 20], "type": "location"}]}
{"tokens": ["Come", "out", "and", "support", "Raw", "Illest", "and", "Storm", "April", "14th", "at", "the", "Whiskey", "with", "Classified", "!"], "entity": [{"text": "Raw Illest", "offset": [4, 6], "type": "group"}, {"text": "Storm", "offset": [7, 8], "type": "group"}, {"text": "the Whiskey", "offset": [11, 13], "type": "location"}]}
{"tokens": ["...", "and", "the", "rules", "are", "?", "#corny", "RT", "@barzangi", ":", "I've", "said", "it", "before", "and", "I'll", "say", "it", "again", ":", "Indian", "food", "RULES", "."], "entity": [{"text": "Indian", "offset": [20, 21], "type": "location"}]}
{"tokens": ["You", "Get", "What", "You", "Give", "~", "Zac", "Brown", "Band", "40", "days", "in", "the", "top", "100", "Release", "Date", ":", "September", "21", ",", "2010Buy", "new", ":", "$", "18.98", "$", "...", "[URL]"], "entity": [{"text": "Zac Brown Band", "offset": [6, 9], "type": "group"}]}
{"tokens": ["All", "I", "want", "in", "life", "is", "mod", "sun", "tickets"], "entity": [{"text": "mod sun", "offset": [6, 8], "type": "group"}]}
{"tokens": ["Headed", "to", "Davidson", "vs", "Blount", "with", "Bennett-", "love", "spending", "time", "with", "my", "son", "!"], "entity": [{"text": "Davidson", "offset": [2, 3], "type": "group"}, {"text": "Blount", "offset": [4, 5], "type": "group"}, {"text": "Bennett-", "offset": [6, 7], "type": "person"}]}
{"tokens": ["@jaredleto", "...", "ive", "been", "to", "13", "30stm", "concerts", "now", "and", "you", "never", "got", "me", "on", "stage", "during/before", "kings", "and", "queens", ":(", "(("], "entity": [{"text": "30stm", "offset": [6, 7], "type": "group"}, {"text": "kings and queens", "offset": [17, 20], "type": "group"}]}
{"tokens": [":", "4th", "ODI", "Match", "PAK", "vs", "NZ", "Target", "300", "Pak", "189/5", "Overs", "38", "Younus", "89*", "Afridi", "12*"], "entity": [{"text": "PAK", "offset": [4, 5], "type": "group"}, {"text": "NZ", "offset": [6, 7], "type": "group"}]}
{"tokens": ["I", "love", "it", ",", "I", "can", "torment", "my", "friends", "and", "their", "kids", "long", "distance", "via", "fb", "and", "twitter", ".", "Mwahaha", "!"], "entity": [{"text": "fb", "offset": [15, 16], "type": "corporation"}, {"text": "twitter", "offset": [17, 18], "type": "corporation"}]}
{"tokens": ["RT", "@BunBTrillOG", ":", "Okay", "#teamtrill", "time", "to", "show", "them", "our", "power", "!", "#BunB106andPark", "needs", "to", "trend", "now", "!", "RT", "til", "it", "hurts", "!", "I", "got", "ya", "twitter", "jail", "..."], "entity": [{"text": "twitter", "offset": [26, 27], "type": "corporation"}]}
{"tokens": ["'RT", "@ItsTheTeenLife", ":", "I", "remember", "when", "myspace", "was", "a", "big", "\"", "who", "has", "the", "most", "free", "time", "on", "their", "hands", "to", "make", "their", "page", "look", "the", "coolest", "\"", "comp", "...'"], "entity": [{"text": "myspace", "offset": [6, 7], "type": "corporation"}]}
{"tokens": ["RT", "@ezraklein", ":", "It", "'s", "Yom", "Kippur", "eve", ",", "so", "it", "'s", "the", "time", "to", "apologize", "to", "anyone", "I've", "wronged", ".", "Hopefully", ",", "you're", "on", "Twitter", ".", "Sorry", "!"], "entity": [{"text": "Twitter", "offset": [25, 26], "type": "corporation"}]}
{"tokens": ["Our", "Favorite", "YouTube", "Videos", "This", "Week", ":", "The", "Drama", "Edition", ":", "Had", "any", "epic", "meltdowns", "this", "week", "?", "You", "know", ",", "of", "the", "cryin", "...", "[URL]"], "entity": [{"text": "YouTube", "offset": [2, 3], "type": "corporation"}]}
{"tokens": ["#Cartier", "-", "Cartier", "Must", "21", "2", "TONE", "MENS", "Watch", "+", "CARTIER", "BOX", "MId", "Size", ":", "$", "800.00", "(", "0", "Bids)End", "Date", ":", "Sat", "...", "[URL]", "#Deals_US"], "entity": [{"text": "Cartier Must 21 2 TONE MENS Watch + CARTIER BOX MId Size", "offset": [2, 14], "type": "product"}]}
{"tokens": ["There", "'s", "a", "lot", "of", "people", "showing", "off", "their", "iPhones", "on", "facebook", "today", ",", "so", "&lt;", "so", "is", "at", "such", "a", "place", ",", "it", "'s", "really", "not", "that", "interesting", ";o", ")"], "entity": [{"text": "iPhones", "offset": [9, 10], "type": "product"}, {"text": "facebook", "offset": [11, 12], "type": "corporation"}]}
{"tokens": ["Posted", "a", "new", "blog", "today", "about", "the", "new", "Lounge22", "Powered", "by", "CORT", "collection", "!", "The", "furniture", "is", "divine", ":", "[URL]"], "entity": [{"text": "Lounge22", "offset": [8, 9], "type": "product"}, {"text": "CORT", "offset": [11, 12], "type": "corporation"}]}
{"tokens": ["Dinner", "tonight", ":", "Gnocchi", "with", "Italian", "Sausage", ",", "Swiss", "Chard", "and", "Ripe", "Tomatoes", "!"], "entity": [{"text": "Gnocchi", "offset": [3, 4], "type": "product"}, {"text": "Italian Sausage", "offset": [5, 7], "type": "product"}, {"text": "Swiss Chard", "offset": [8, 10], "type": "product"}, {"text": "Tomatoes", "offset": [12, 13], "type": "product"}]}
{"tokens": ["FAN", "Art", "in", "Club", "Penguin", ":)", ":", "Here", "are", "this", "weeks", "Club", "Penguin", "FUN", "Art", "Drawings", ":)", "The", "Snow", "Fort", "is", "a", "Super", "FUN", "Plac", "...", "[URL]"], "entity": [{"text": "Club Penguin", "offset": [3, 5], "type": "product"}, {"text": "Club Penguin", "offset": [11, 13], "type": "product"}]}
{"tokens": ["Citizens", "of", "Earth", "up", "on", "Steam", "and", "due", "the", "20th", ".", "Part", "of", "me", "wants", "to", "name", "the", "VP", "Richard", "Hawk", ".", "[URL]", "[URL]"], "entity": [{"text": "Citizens of Earth", "offset": [0, 3], "type": "creative_work"}, {"text": "Richard Hawk", "offset": [19, 21], "type": "person"}]}
{"tokens": ["Have", "DJ", "Got", "Us", "Fallin", "in", "Love", "in", "my", "head", ".", "\"", "Cause", "baby", "tonight", ",", "The", "dj", "got", "us", "fallin", "in", "love", "again", "\""], "entity": [{"text": "DJ Got Us Fallin in Love", "offset": [1, 7], "type": "creative_work"}]}
{"tokens": ["@DoctorWho_BBCA", "Last", "Christmas", "is", "as", "brilliant", "the", "2nd", "time", "as", "it", "was", "the", "1st", "!", "#DoctorWho", "#doctorwhochristmas", "#LastChristmas"], "entity": [{"text": "Last Christmas", "offset": [1, 3], "type": "creative_work"}]}
{"tokens": ["@_Flik_", "awww", "he", "'s", "in", "the", "rocky", "horror", "show", "next", "week", "which", "means", "he", "'s", "gotta", "wear", "stockings", "an", "suspenders", "lol", ":P"], "entity": [{"text": "rocky horror show", "offset": [6, 9], "type": "creative_work"}]}
{"tokens": ["@wodekkut", "11", "feb", "..", "to", "promote", "his", "film", "with", "jackie", "chan", "\"", "dragon", "blade", "\""], "entity": [{"text": "jackie chan", "offset": [9, 11], "type": "person"}, {"text": "dragon blade", "offset": [12, 14], "type": "creative_work"}]}
